councilcount/__init__.py
councilcount/_estimates_by_geography_function.py
councilcount/_gen_percent_estimate_function.py
councilcount/_gen_proportion_MOE_function.py
councilcount/_generate_bbl_estimates_function.py
councilcount/_generate_bbl_variances_function.py
councilcount/_get_MOE_and_CV_function.py
councilcount/_reorder_columns_function.py
councilcount/gen_percent_MOE_function.py
councilcount/generate_new_estimates_function.py
councilcount/get_ACS_variables_function.py
councilcount/get_bbl_estimates_function.py
councilcount/get_geo_estimates_function.py
councilcount/pull_census_api_codes_function.py
councilcount/data/bbl-population-estimates_2011.csv
councilcount/data/bbl-population-estimates_2016.csv
councilcount/data/bbl-population-estimates_2021.csv
councilcount/data/bbl-population-estimates_2022.csv
councilcount/data/borough-geographies_2011.geojson
councilcount/data/borough-geographies_2016.geojson
councilcount/data/borough-geographies_2021.geojson
councilcount/data/borough-geographies_2022.geojson
councilcount/data/communitydist-boundaries.geojson
councilcount/data/communitydist-geographies_2011.geojson
councilcount/data/communitydist-geographies_2016.geojson
councilcount/data/communitydist-geographies_2021.geojson
councilcount/data/communitydist-geographies_2022.geojson
councilcount/data/councildist-geographies_b13_2011.geojson
councilcount/data/councildist-geographies_b13_2016.geojson
councilcount/data/councildist-geographies_b13_2021.geojson
councilcount/data/councildist-geographies_b13_2022.geojson
councilcount/data/councildist-geographies_b23_2011.geojson
councilcount/data/councildist-geographies_b23_2016.geojson
councilcount/data/councildist-geographies_b23_2021.geojson
councilcount/data/councildist-geographies_b23_2022.geojson
councilcount/data/councildist_2013-boundaries.geojson
councilcount/data/councildist_2023-boundaries.geojson
councilcount/data/data_dictionary_2011.csv
councilcount/data/data_dictionary_2016.csv
councilcount-2.0.0.dist-info/METADATA
councilcount-2.0.0.dist-info/WHEEL
councilcount-2.0.0.dist-info/top_level.txt
councilcount-2.0.0.dist-info/RECORD
